MANIFEST.in
setup.py
sikuli/__init__.py
sikuli/sikuli-api-1.0.2-standalone.jar
sikuli/sikuli.py
sikuli.egg-info/PKG-INFO
sikuli.egg-info/SOURCES.txt
sikuli.egg-info/dependency_links.txt
sikuli.egg-info/requires.txt
sikuli.egg-info/top_level.txt