Metadata-Version: 1.1
Name: sikuli
Version: 0.1
Summary: A CPython wrapper around the sikuli standalone jar
Home-page: https://github.com/kevlened/sikuli_cpython
Author: Len Boyette
Author-email: boyettel+sikuli@gmail.com
License: UNKNOWN
Keywords: testing
Platform: UNKNOWN
Classifier: Programming Language :: Python
Classifier: License :: OSI Approved :: MIT License
Classifier: Operating System :: OS Independent
Classifier: Topic :: Software Development :: Libraries :: Python Modules
Classifier: Topic :: Software Development :: Quality Assurance
Classifier: Topic :: Software Development :: Testing
Classifier: Intended Audience :: Developers
Classifier: Development Status :: 4 - Beta
Requires: jnius
